{
    "configurations": [
        {
            "name": "Win32",
            "includePath": [
                "${workspaceFolder}/**"
            ],
            "defines": [
                "_DEBUG",
                "COBJMACROS"
            ],
            "windowsSdkVersion": "10.0.19041.0",
            "compilerPath": "C:/Program Files (x86)/Microsoft Visual Studio/2019/BuildTools/VC/Tools/MSVC/14.29.30037/bin/Hostx64/x64/cl.exe",
            "intelliSenseMode": "windows-msvc-x64",
            "cStandard": "c17",
            "cppStandard": "c++17",
            "compilerArgs": [
                "-std:c17",
                "-permissive-",
                "-TC"
            ]
        }
    ],
    "version": 4
}